<?xml version='1.0' encoding='UTF-8'?>
<song xmlns="http://openlyrics.info/namespace/2009/song" version="0.8" createdIn="OpenLP 3.0.2" modifiedIn="OpenLP 3.0.2" modifiedDate="2024-02-13T20:39:19">
  <properties>
    <titles>
      <title>U U U NA</title>
      <title>U U U Na</title>
    </titles>
    <authors>
      <author type="words">Autor Nieznany 2</author>
    </authors>
  </properties>
  <lyrics>
    <verse name="v1a">
      <lines>Chcę śpiewać wciaż <br/>I nawet gdy nadejdzie noc<br/>Nie przestanę wielbić Cię<br/>Panie kocham Cię<br/><br/></lines>
    </verse>
    <verse name="v1b">
      <lines>U U U Na Na Na Na Na (...)</lines>
    </verse>
    <verse name="v1c">
      <lines>Mój Stworzycielu !<br/>Chcę dziękować Ci<br/>Z całej duszy swej<br/>I całym sercem swym</lines>
    </verse>
  </lyrics>
</song>
